CHANGELOG.rst
LICENSE
MANIFEST.in
README.rst
extras_requirements.json
requirements.txt
setup.py
docs/Makefile
docs/changelog.rst
docs/conf.py
docs/example.rst
docs/index.rst
docs/make.bat
docs/readme.rst
docs/source/modules.rst
docs/source/paralytics.preprocessing.rst
docs/source/paralytics.rst
docs/source/paralytics.utils.rst
docs/source/paralytics.xai.rst
docs/source/reference/decorators.rst
docs/source/reference/exceptions.rst
docs/source/reference/generals.rst
docs/source/reference/index.rst
docs/source/reference/preprocessing.rst
docs/source/reference/utils.rst
docs/source/reference/xai.rst
docs/source/reference/api/paralytics.CorrelationReducer.rst
docs/source/reference/api/paralytics.Discretizer.rst
docs/source/reference/api/paralytics.NothingSelectedWarning.rst
docs/source/reference/api/paralytics.PandasFeatureUnion.rst
docs/source/reference/api/paralytics.TargetEncoder.rst
docs/source/reference/api/paralytics.UniqueValuesError.rst
docs/source/reference/api/paralytics.VIFSelector.rst
docs/source/reference/api/paralytics.force_context_manager.rst
docs/source/reference/api/paralytics.preprocessing.CategoricalBinarizer.rst
docs/source/reference/api/paralytics.preprocessing.CategoricalGrouper.rst
docs/source/reference/api/paralytics.preprocessing.ColumnProjector.rst
docs/source/reference/api/paralytics.preprocessing.ColumnSelector.rst
docs/source/reference/api/paralytics.preprocessing.Imputer.rst
docs/source/reference/api/paralytics.preprocessing.TypeSelector.rst
docs/source/reference/api/paralytics.utils.BaseSeleniumBrowser.rst
docs/source/reference/api/paralytics.utils.check_column_existence.rst
docs/source/reference/api/paralytics.utils.check_continuity.rst
docs/source/reference/api/paralytics.utils.check_is_dataframe.rst
docs/source/reference/api/paralytics.utils.check_prime.rst
docs/source/reference/api/paralytics.utils.check_uniq.rst
docs/source/reference/api/paralytics.utils.custom_round.rst
docs/source/reference/api/paralytics.utils.find_sparsity.rst
paralytics.egg-info/PKG-INFO
paralytics.egg-info/SOURCES.txt
paralytics.egg-info/dependency_links.txt
paralytics.egg-info/requires.txt
paralytics.egg-info/top_level.txt
paralytics.egg-info/zip-safe
