Metadata-Version: 2.1
Name: paralytics
Version: 0.3.2
Summary: Python analytical scripts that will overcome paralysis in your data analysis.
Home-page: https://mrtovsky.github.io/Paralytics/
Author: Mateusz Zakrzewski, Łukasz Bala
Author-email: paralytics@gmail.com
License: MIT
Platform: UNKNOWN
Provides-Extra: vif
Provides-Extra: plot
Provides-Extra: browser
Provides-Extra: all
